paddle_rifle/rifle.py
paddle_rifle-0.21.dist-info/LICENSE
paddle_rifle-0.21.dist-info/METADATA
paddle_rifle-0.21.dist-info/WHEEL
paddle_rifle-0.21.dist-info/top_level.txt
paddle_rifle-0.21.dist-info/RECORD
